{"realLevels": {"attack": 60, "strength": 90, "defence": 1, "ranged": 90, "magic": 94, "prayer": 52, "hitpoints": 85}, "boostedLevels": {"attack": 60, "strength": 90, "defence": 1, "ranged": 90, "magic": 94, "prayer": 52, "hitpoints": 85}, "prayerUnlocks": {"kingsRansom": false, "rigour": false, "augury": false, "deadeye": false, "mysticVigour": false}, "requirements": {"skills": {"ATTACK": 60, "STRENGTH": 90, "DEFENCE": 1, "RANGED": 90, "MAGIC": 94, "PRAYER": 52, "HITPOINTS": 85}, "quests": ["MONKEY_MADNESS_I", "ANIMAL_MAGNETISM", "DESERT_TREASURE_I"]}, "owned": {"4587": 1, "1215": 1, "5698": 1, "10551": 1, "1127": 1, "861": 1, "12788": 1, "892": 1000, "11212": 300, "6585": 1, "2503": 1, "1129": 1, "24177": 1, "12926": 1, "811": 2000, "20997": 1, "27275": 1, "26219": 1, "13652": 1, "12006": 1}, "bankScanned": true}